ek_geo/__init__.py
ek_geo/datastructs.py
ek_geo-0.2.1.dist-info/METADATA
ek_geo-0.2.1.dist-info/WHEEL
ek_geo-0.2.1.dist-info/RECORD
