Metadata-Version: 2.3
Name: ek-geo
Version: 0.2.1
Summary: Geographic utilities for EarthKit
Author-email: Jett Chen <jettchen12345@gmail.com>
License-Expression: MIT
Requires-Python: >=3.8
Requires-Dist: geopy>=2.4.1
Requires-Dist: pydantic>=2.8.2
Provides-Extra: graphing
Requires-Dist: pydeck; extra == 'graphing'
